MANIFEST.in
README.rst
requirements.txt
setup.py
thoth/digests_fetcher/__init__.py
thoth/digests_fetcher/base.py
thoth/digests_fetcher/cli.py
thoth/digests_fetcher/exceptions.py
thoth/digests_fetcher/python/__init__.py
thoth/digests_fetcher/python/fetch.py
thoth_digests_fetcher.egg-info/PKG-INFO
thoth_digests_fetcher.egg-info/SOURCES.txt
thoth_digests_fetcher.egg-info/dependency_links.txt
thoth_digests_fetcher.egg-info/entry_points.txt
thoth_digests_fetcher.egg-info/not-zip-safe
thoth_digests_fetcher.egg-info/requires.txt
thoth_digests_fetcher.egg-info/top_level.txt